experimental/__init__.py
experimental/__main__.py
experimental/version.py
experimental/core/__init__.py
experimental/core/console.py
experimental/core/import_hook.py
experimental/core/transforms.py
experimental/transformers/__init__.py
experimental/transformers/approx.py
experimental/transformers/convert_py2.py
experimental/transformers/decrement.py
experimental/transformers/french_syntax.py
experimental/transformers/function_keyword.py
experimental/transformers/increment.py
experimental/transformers/int_seq.py
experimental/transformers/nobreak_keyword.py
experimental/transformers/pep542.py
experimental/transformers/print_keyword.py
experimental/transformers/repeat_keyword.py
experimental/transformers/spanish_syntax.py
experimental/transformers/switch_statement.py
experimental/transformers/where_clause.py
experimental/transformers/utils/__init__.py
experimental/transformers/utils/one2one.py
experimental/transformers/utils/shared.py
experimental/transformers/utils/simple2to3.py
experimental-0.9.7.dist-info/DESCRIPTION.rst
experimental-0.9.7.dist-info/METADATA
experimental-0.9.7.dist-info/RECORD
experimental-0.9.7.dist-info/WHEEL
experimental-0.9.7.dist-info/metadata.json
experimental-0.9.7.dist-info/top_level.txt
tests/__init__.py
tests/approx_testfile.py
tests/common.py
tests/decrement_testfile.py
tests/french_testfile.py
tests/function_testfile.py
tests/increment_testfile.py
tests/int_seq_testfile.py
tests/multiple_testfile.py
tests/nobreak_testfile.py
tests/pep542_testfile.py
tests/print_testfile.py
tests/repeat_testfile.py
tests/spanish_testfile.py
tests/switch_testfile.py
tests/test_a_console.py
tests/test_approx.py
tests/test_decrement.py
tests/test_french.py
tests/test_function.py
tests/test_increment.py
tests/test_int_seq.py
tests/test_multiple_transforms.py
tests/test_nobreak.py
tests/test_pep542.py
tests/test_print_keyword.py
tests/test_repeat.py
tests/test_switch.py
tests/test_where.py
tests/where_testfile.py
