Metadata-Version: 2.0
Name: experimental
Version: 0.9.7
Summary: Enables easy modification of Python's syntax on the fly.
Home-page: https://github.com/aroberge/experimental
Author: André Roberge
Author-email: Andre.Roberge@gmail.com
License: MIT
